{
  "version": "1.0.27",
  "date": "2026-06-14",
  "summaryBullets": [
    "fix(mobile): keep v1.0.26 notes release-specific (#358)",
    "chore(mobile): auto-release bump to v1.0.26 (after 7e682f8) (#357)"
  ],
  "sections": [
    {
      "title": "Changes",
      "bullets": [
        {
          "text": "fix(mobile): keep v1.0.26 notes release-specific (#358)"
        },
        {
          "text": "chore(mobile): auto-release bump to v1.0.26 (after 7e682f8) (#357)"
        }
      ]
    },
    {
      "title": "Release metadata",
      "bullets": [
        {
          "text": "Repository: yanniedog/AR-local"
        },
        {
          "text": "Version tag: app-v1.0.27"
        },
        {
          "text": "Since tag: app-v1.0.25"
        }
      ]
    }
  ]
}
